[null,{"name":"startup","temp":"","event-type":"1","_id":"hbmpL","actions":[{"url":"resources/1.png","storage":"3","varName":"1","name":"Create Image"},{"url":"resources/2.png","storage":"3","varName":"2","name":"Create Image"},{"url":"resources/3.png","storage":"3","varName":"3","name":"Create Image"},{"url":"resources/4.png","storage":"3","varName":"4","name":"Create Image"},{"url":"resources/5.png","storage":"3","varName":"5","name":"Create Image"},{"url":"resources/6.png","storage":"3","varName":"6","name":"Create Image"},{"url":"resources/7.png","storage":"3","varName":"7","name":"Create Image"},{"url":"resources/8.png","storage":"3","varName":"8","name":"Create Image"},{"url":"resources/9.png","storage":"3","varName":"9","name":"Create Image"},{"url":"resources/10.png","storage":"3","varName":"10","name":"Create Image"},{"url":"resources/reel.png","storage":"3","varName":"reel","name":"Create Image"},{"url":"resources/reeloverlay.png","storage":"3","varName":"reeloverlay","name":"Create Image"},{"url":"resources/result.png","storage":"3","varName":"result","name":"Create Image"},{"url":"resources/lane1.png","storage":"3","varName":"lane1","name":"Create Image"},{"url":"resources/lane2.png","storage":"3","varName":"lane2","name":"Create Image"},{"url":"resources/lane3.png","storage":"3","varName":"lane3","name":"Create Image"},{"url":"resources/lane4.png","storage":"3","varName":"lane4","name":"Create Image"},{"url":"resources/lane5.png","storage":"3","varName":"lane5","name":"Create Image"},{"storage":"2","varName":"rolling","changeType":"0","value":"0","name":"Control Variable"}]},{"name":"NewEvent","temp":"","event-type":"6","_id":"AgLKy","actions":[{"channel":"4","varName":"","message":"```\n|________________________________________________________|\n| WELCOME!                                               |\n| If this is your first time on the server, please use   |\n| the command \"!register\" to get yourself started!       |\n| (using this command second time resets your chips)     |\n|________________________________________________________|\n| -  !lanes - displays the paying lanes and a paytable   |\n|  -  !spin  - to spin the slot machine!                 |\n|________________________________________________________|\n```","storage":"0","varName2":"","name":"Send Message"}]}]